assistant_project/__init__.py
assistant_project/dict_wrapper/__init__.py
assistant_project/dict_wrapper/dict_wrapper.py
assistant_project/dict_wrapper/utils.py
assistant_project/graphdb/__init__.py
assistant_project/graphdb/graph_db.py
assistant_project/graphdb/onto_refine.py
assistant_project/graphdb/utils.py
assistant_project/production_system/__init__.py
assistant_project/production_system/file_reader.py
assistant_project/production_system/opg_list.py
assistant_project/production_system/osg_list.py
assistant_project/production_system/production_system.py
assistant_project/production_system/resource_list.py
assistant_project/production_system/utils.py
assistant_project-0.3.8.dist-info/LICENCE
assistant_project-0.3.8.dist-info/METADATA
assistant_project-0.3.8.dist-info/WHEEL
assistant_project-0.3.8.dist-info/top_level.txt
assistant_project-0.3.8.dist-info/RECORD
