Metadata-Version: 2.1
Name: assistant-project
Version: 0.3.8
Summary: Python Library for the EU ASSISTANT-Project
Author-email: Nikolas Laudenbach <nikolas.laudenbach@tum.de>
License: Copyright (c) 2018 The Python Packaging Authority
Project-URL: homepage, https://assistant-project.eu
Project-URL: repository, https://gitlab.lrz.de/pd/pd.graphdbmapping/python-library.git
Keywords: graphdb,assistant
Classifier: Programming Language :: Python :: 3
Classifier: Operating System :: OS Independent
Requires-Python: >=3.7
License-File: LICENCE
